LICENSE
setup.cfg
setup.py
aiee/__init__.py
aiee/arg.py
aiee/numbers.py
aiee.egg-info/PKG-INFO
aiee.egg-info/SOURCES.txt
aiee.egg-info/dependency_links.txt
aiee.egg-info/entry_points.txt
aiee.egg-info/top_level.txt
aiee/runnable/flags.py
aiee/runnable/main.py
tests/test_arg.py
tests/test_flag.py
tests/test_numbers.py