Metadata-Version: 2.1
Name: aiee
Version: 0.3.2
Summary: Common command line interfacing utils
Home-page: https://git.defalsify.org/aiee
Author: Louis Holbrook
Author-email: dev@holbrook.no
License: WTFPL
Keywords: cli
Classifier: Programming Language :: Python :: 3
Classifier: Operating System :: OS Independent
Classifier: Development Status :: 3 - Alpha
Classifier: Environment :: Console
Classifier: Intended Audience :: Developers
Classifier: License :: OSI Approved :: GNU General Public License v3 or later (GPLv3+)
Requires-Python: >=3.6
License-File: LICENSE
